universal_agent_nexus/__init__.py
universal_agent_nexus/builder.py
universal_agent_nexus/compiler.py
universal_agent_nexus/enrichment.py
universal_agent_nexus/generator_registry.py
universal_agent_nexus/manifest.py
universal_agent_nexus/parser_registry.py
universal_agent_nexus/adapters/__init__.py
universal_agent_nexus/adapters/base.py
universal_agent_nexus/adapters/aws/__init__.py
universal_agent_nexus/adapters/aws/dynamodb_store.py
universal_agent_nexus/adapters/aws/runtime.py
universal_agent_nexus/adapters/aws/step_functions.py
universal_agent_nexus/adapters/langgraph/__init__.py
universal_agent_nexus/adapters/langgraph/batch_accumulator.py
universal_agent_nexus/adapters/langgraph/compiler.py
universal_agent_nexus/adapters/langgraph/factory.py
universal_agent_nexus/adapters/langgraph/runtime.py
universal_agent_nexus/adapters/mcp/__init__.py
universal_agent_nexus/adapters/mcp/server.py
universal_agent_nexus/adapters/uaa/__init__.py
universal_agent_nexus/adapters/uaa/compiler.py
universal_agent_nexus/adapters/uaa/runtime.py
universal_agent_nexus/bridges/__init__.py
universal_agent_nexus/bridges/fabric_to_arch.py
universal_agent_nexus/cache_fabric/__init__.py
universal_agent_nexus/cache_fabric/base.py
universal_agent_nexus/cache_fabric/defaults.py
universal_agent_nexus/cache_fabric/factory.py
universal_agent_nexus/cache_fabric/nexus_integration.py
universal_agent_nexus/cache_fabric/runtime_integration.py
universal_agent_nexus/cache_fabric/backends/__init__.py
universal_agent_nexus/cache_fabric/backends/memory.py
universal_agent_nexus/cache_fabric/backends/redis_backend.py
universal_agent_nexus/cache_fabric/backends/vector_backend.py
universal_agent_nexus/cli/__init__.py
universal_agent_nexus/cli/compile.py
universal_agent_nexus/cli/main.py
universal_agent_nexus/ir/__init__.py
universal_agent_nexus/ir/annotations.py
universal_agent_nexus/ir/factories.py
universal_agent_nexus/ir/generator.py
universal_agent_nexus/ir/parser.py
universal_agent_nexus-3.2.0.dist-info/METADATA
universal_agent_nexus-3.2.0.dist-info/WHEEL
universal_agent_nexus-3.2.0.dist-info/entry_points.txt
universal_agent_nexus-3.2.0.dist-info/RECORD
