Metadata-Version: 2.4
Name: universal-agent-nexus
Version: 3.2.0
Summary: The Translation Layer: Compile Universal Agents to AWS, LangGraph, MCP, or UAA Kernel.
Requires-Python: >=3.11
Requires-Dist: httpx>=0.25.0
Requires-Dist: pydantic>=2.9.0
Requires-Dist: pyyaml>=6.0
Requires-Dist: simpleeval>=1.0.0
Requires-Dist: typer>=0.12.0
Requires-Dist: universal-agent-arch>=0.3.0
Requires-Dist: universal-agent-fabric>=0.2.1
Provides-Extra: all
Requires-Dist: boto3>=1.34.0; extra == 'all'
Requires-Dist: fastapi>=0.115.0; extra == 'all'
Requires-Dist: langchain-anthropic>=0.2.0; extra == 'all'
Requires-Dist: langchain-core>=0.2.0; extra == 'all'
Requires-Dist: langchain-mcp-adapters>=0.1.0; extra == 'all'
Requires-Dist: langchain-ollama>=0.2.0; extra == 'all'
Requires-Dist: langchain-openai>=0.2.0; extra == 'all'
Requires-Dist: langgraph-checkpoint-postgres>=2.0.0; extra == 'all'
Requires-Dist: langgraph>=0.2.0; extra == 'all'
Requires-Dist: mcp>=1.0.0; extra == 'all'
Requires-Dist: opentelemetry-api>=1.20.0; extra == 'all'
Requires-Dist: opentelemetry-exporter-otlp>=1.20.0; extra == 'all'
Requires-Dist: opentelemetry-instrumentation-fastapi>=0.41b0; extra == 'all'
Requires-Dist: opentelemetry-sdk>=1.20.0; extra == 'all'
Requires-Dist: psycopg-pool>=3.2.0; extra == 'all'
Requires-Dist: psycopg[binary]>=3.2.0; extra == 'all'
Requires-Dist: uvicorn>=0.30.0; extra == 'all'
Provides-Extra: anthropic
Requires-Dist: langchain-anthropic>=0.2.0; extra == 'anthropic'
Provides-Extra: aws
Requires-Dist: boto3>=1.34.0; extra == 'aws'
Provides-Extra: dev
Requires-Dist: moto[dynamodb]>=5.0.0; extra == 'dev'
Requires-Dist: mypy>=1.8.0; extra == 'dev'
Requires-Dist: pytest-asyncio>=0.23.0; extra == 'dev'
Requires-Dist: pytest-cov>=4.1.0; extra == 'dev'
Requires-Dist: pytest>=8.0.0; extra == 'dev'
Requires-Dist: ruff>=0.8.0; extra == 'dev'
Requires-Dist: testcontainers>=4.0.0; extra == 'dev'
Provides-Extra: langgraph
Requires-Dist: langchain-core>=0.2.0; extra == 'langgraph'
Requires-Dist: langchain-mcp-adapters>=0.1.0; extra == 'langgraph'
Requires-Dist: langchain-openai>=0.2.0; extra == 'langgraph'
Requires-Dist: langgraph-checkpoint-postgres>=2.0.0; extra == 'langgraph'
Requires-Dist: langgraph>=0.2.0; extra == 'langgraph'
Requires-Dist: psycopg-pool>=3.2.0; extra == 'langgraph'
Requires-Dist: psycopg[binary]>=3.2.0; extra == 'langgraph'
Provides-Extra: mcp
Requires-Dist: fastapi>=0.115.0; extra == 'mcp'
Requires-Dist: mcp>=1.0.0; extra == 'mcp'
Requires-Dist: uvicorn>=0.30.0; extra == 'mcp'
Provides-Extra: observability
Requires-Dist: opentelemetry-api>=1.20.0; extra == 'observability'
Requires-Dist: opentelemetry-exporter-otlp>=1.20.0; extra == 'observability'
Requires-Dist: opentelemetry-instrumentation-fastapi>=0.41b0; extra == 'observability'
Requires-Dist: opentelemetry-sdk>=1.20.0; extra == 'observability'
Provides-Extra: ollama
Requires-Dist: langchain-ollama>=0.2.0; extra == 'ollama'
